trigdeg/__init__.py
trigdeg/trigdeg.py
trigdeg-0.1.0.dist-info/LICENSE
trigdeg-0.1.0.dist-info/METADATA
trigdeg-0.1.0.dist-info/WHEEL
trigdeg-0.1.0.dist-info/top_level.txt
trigdeg-0.1.0.dist-info/RECORD
